{
  "kind": "singleType",
  "collectionName": "globals",
  "info": {
    "singularName": "global",
    "pluralName": "globals",
    "displayName": "Global",
    "name": "global",
    "description": ""
  },
  "options": {
    "increments": true,
    "timestamps": true,
    "draftAndPublish": false
  },
  "pluginOptions": {
    "i18n": {
      "localized": true
    }
  },
  "attributes": {
    "siteName": {
      "type": "string",
      "required": true,
      "pluginOptions": {
        "i18n": {
          "localized": true
        }
      }
    },
    "siteTagline": {
      "pluginOptions": {
        "i18n": {
          "localized": true
        }
      },
      "type": "string",
      "required": true
    },
    "defaultSeo": {
      "type": "component",
      "repeatable": false,
      "component": "shared.seo",
      "required": true,
      "pluginOptions": {
        "i18n": {
          "localized": true
        }
      }
    },
    "contactButton": {
      "displayName": "contactButton",
      "type": "component",
      "repeatable": false,
      "component": "shared.contact-button",
      "pluginOptions": {
        "i18n": {
          "localized": true
        }
      }
    },
    "contactOptions": {
      "displayName": "contactOptions",
      "type": "component",
      "repeatable": true,
      "pluginOptions": {
        "i18n": {
          "localized": true
        }
      },
      "component": "shared.contact-options"
    },
    "contactTitle": {
      "pluginOptions": {
        "i18n": {
          "localized": true
        }
      },
      "type": "string"
    },
    "contactDescription": {
      "pluginOptions": {
        "i18n": {
          "localized": true
        }
      },
      "type": "text"
    },
    "footerTitle": {
      "pluginOptions": {
        "i18n": {
          "localized": true
        }
      },
      "type": "string"
    },
    "contactConfirmation": {
      "pluginOptions": {
        "i18n": {
          "localized": true
        }
      },
      "type": "string"
    }
  }
}
